checkio_executor_python
