Metadata-Version: 1.1
Name: checkio-executor-python
Version: 0.0.9
Summary: CheckiO module for execute python code
Home-page: https://github.com/CheckiO/checkio-executor-python
Author: CheckiO
Author-email: igor@checkio.org
License: UNKNOWN
Download-URL: https://github.com/CheckiO/checkio-executor-python/tarball/0.0.9
Platform: UNKNOWN
